human_eval/__init__.py
human_eval/api_client.py
human_eval/cli.py
human_eval/config.py
human_eval/registry.py
human_eval/runner.py
human_eval/solvers.py
human_eval/transform.py
he_eval-0.1.1.dist-info/METADATA
he_eval-0.1.1.dist-info/WHEEL
he_eval-0.1.1.dist-info/entry_points.txt
he_eval-0.1.1.dist-info/RECORD
