Metadata-Version: 2.4
Name: he-eval
Version: 0.1.1
Summary: Human evaluation for Control Arena settings
Requires-Python: >=3.11
Requires-Dist: click>=8.0
Requires-Dist: control-arena==11.4.0
Requires-Dist: httpx>=0.24
Requires-Dist: inspect-ai==0.3.151
Provides-Extra: dev
Requires-Dist: httpx>=0.24; extra == 'dev'
Requires-Dist: pytest-asyncio>=0.21.0; extra == 'dev'
Requires-Dist: pytest>=7.0.0; extra == 'dev'
Provides-Extra: e2e
Requires-Dist: aiosqlite>=0.19.0; extra == 'e2e'
Requires-Dist: bcrypt<4.1.0,>=4.0.0; extra == 'e2e'
Requires-Dist: fastapi>=0.104.0; extra == 'e2e'
Requires-Dist: greenlet>=3.0.0; extra == 'e2e'
Requires-Dist: passlib[bcrypt]>=1.7.4; extra == 'e2e'
Requires-Dist: pydantic-settings>=2.0.0; extra == 'e2e'
Requires-Dist: pydantic[email]>=2.5.0; extra == 'e2e'
Requires-Dist: python-jose[cryptography]>=3.3.0; extra == 'e2e'
Requires-Dist: sqlalchemy[asyncio]>=2.0.0; extra == 'e2e'
Requires-Dist: uvicorn[standard]>=0.24.0; extra == 'e2e'
